Metadata-Version: 2.1
Name: ebyte-lora-e22
Version: 0.0.3
Summary: MicroPython LoRa EBYTE E22 device library complete and tested with Arduino SAMD, esp8266, esp32, Raspberry, rp2040 and STM32. sx1262/sx1268
Home-page: https://github.com/xreef/EByte_LoRa_E22_micropython_library
Author: Renzo Mischianti
Author-email: Renzo Mischianti <renzo@mischianti.org>
Maintainer: Renzo Mischianti
Maintainer-email: Renzo Mischianti <renzo@mischianti.org>
License: The MIT License (MIT)
Project-URL: homepage, https://www.mischianti.org
Project-URL: Documentation, https://www.mischianti.org/category/my-libraries/ebyte-lora-e22-devices/
Project-URL: Documentazione, https://www.mischianti.org/it/category/le-mie-librerie/dispositivi-ebyte-lora-e22/
Project-URL: Repository, https://github.com/xreef/EByte_LoRa_E22_micropython_library
Project-URL: Bug Tracker, https://github.com/xreef/EByte_LoRa_E22_micropython_library/issues
Project-URL: Examples, https://github.com/xreef/EByte_LoRa_E22_micropython_library/tree/main/examples
Keywords: LoRa,UART,EByte,esp32,esp8266,stm32,SAMD,Arduino,Raspberry Pi Pico,rp2040,MicroPython,sx1262,sx1268,e22
Classifier: Development Status :: 5 - Production/Stable
Classifier: Programming Language :: Python :: Implementation :: MicroPython
Classifier: License :: OSI Approved :: MIT License
Requires-Python: >=3.7
License-File: LICENSE.md
